{"expireTime":9007200889934663000,"key":"c5eb832cf50d4f8150442f57db79b482","val":{"name":"IMAGE_PROCESSING","inputPaths":["/Users/anhtuantran/Desktop/Gatsby/Monkey_Developers/src/images/pexels-photo-6072557.jpeg"],"outputDir":"/Users/anhtuantran/Desktop/Gatsby/Monkey_Developers/public/static/0d8846997b3cbfa031721e88c7b2aae9","args":{"isLazy":false,"operations":[{"outputPath":"2579c/pexels-photo-6072557.jpg","args":{"height":375,"width":250,"cropFocus":17,"toFormat":"jpg","fit":"cover"}},{"outputPath":"87f6c/pexels-photo-6072557.jpg","args":{"height":749,"width":500,"cropFocus":17,"toFormat":"jpg","fit":"cover"}},{"outputPath":"cd411/pexels-photo-6072557.jpg","args":{"height":1498,"width":1000,"cropFocus":17,"toFormat":"jpg","fit":"cover"}}],"pluginOptions":{"base64Width":20,"forceBase64Format":"","useMozJpeg":false,"stripMetadata":true,"lazyImageGeneration":true,"defaultQuality":50,"failOnError":true,"plugins":[]}}}}